[
    {
        "name1": "بايرن ميونخ",
        "logo1": "https://imgs.ysscores.com/teams/64/2351690288818.png",
        "name2": "أوجسبورغ",
        "logo2": "https://imgs.ysscores.com/teams/64/7221690288817.png",
        "start_time": 1769265000,
        "end_time": 1769272200,
        "champions": "غير معروف",
        "channel": "غير معروف",
        "commentary": "غير معروف",
        "id": "manual_69741f6ba5ac4",
        "match_status": "مباشر",
        "channel_id": "9e7d0edd-459c-42a6-ba0b-0c15274fa42c",
        "section": 1
    },
    {
        "name1": "بيرنلي",
        "logo1": "https://imgs.ysscores.com/teams/64/7301690118156.png",
        "name2": "توتنهام",
        "logo2": "https://imgs.ysscores.com/teams/64/2501692467226.png",
        "start_time": 1769266800,
        "end_time": 1769274000,
        "champions": "غير معروف",
        "channel": "غير معروف",
        "commentary": "غير معروف",
        "id": "manual_69741f8dc3ba9",
        "match_status": "مباشر",
        "channel_id": "f0d5144f-9290-40bc-9cee-d7b820431107",
        "section": 1
    },
    {
        "name1": "فولهام",
        "logo1": "https://imgs.ysscores.com/teams/64/4711690118927.png",
        "name2": "برايتون",
        "logo2": "https://imgs.ysscores.com/teams/64/2271696710594.png",
        "start_time": 1769266800,
        "end_time": 1769274000,
        "champions": "غير معروف",
        "channel": "غير معروف",
        "commentary": "غير معروف",
        "id": "manual_69741f96ae871",
        "match_status": "مباشر",
        "channel_id": "e199d2fb-a128-4065-9621-0300c5e5bc2b",
        "section": 1
    },
    {
        "name1": "مان سيتي",
        "logo1": "https://imgs.ysscores.com/teams/64/4481690118308.png",
        "name2": "وولفرهامبتون",
        "logo2": "https://imgs.ysscores.com/teams/64/9631690118479.png",
        "start_time": 1769266800,
        "end_time": 1769274000,
        "champions": "غير معروف",
        "channel": "غير معروف",
        "commentary": "غير معروف",
        "id": "manual_69741fa3085bd",
        "match_status": "مباشر",
        "channel_id": "d6d19564-6f6b-49a1-b193-dc3c4613b8a3",
        "section": 1
    },
    {
        "name1": "فالنسيا",
        "logo1": "https://imgs.ysscores.com/teams/64/7881690196747.png",
        "name2": "إسبانيول",
        "logo2": "https://imgs.ysscores.com/teams/64/4481690370529.png",
        "start_time": 1769267700,
        "end_time": 1769274900,
        "champions": "غير معروف",
        "channel": "غير معروف",
        "commentary": "غير معروف",
        "id": "manual_69741ffa4c293",
        "match_status": "مباشر",
        "channel_id": "5629d0fa-6cac-47fd-bcb4-c6df271d8a09",
        "section": 1
    },
    {
        "name1": "الخلود",
        "logo1": "https://imgs.ysscores.com/teams/64/5501757530062.png",
        "name2": "الاتفاق",
        "logo2": "https://imgs.ysscores.com/teams/64/1151690298845.png",
        "start_time": 1769268000,
        "end_time": 1769275200,
        "champions": "غير معروف",
        "channel": "غير معروف",
        "commentary": "غير معروف",
        "id": "manual_6974201376969",
        "match_status": "مباشر",
        "channel_id": "7a1287b0-6d27-4040-a79f-98b5b4c6c896",
        "section": 1
    },
    {
        "name1": "شبيبة القبائل",
        "logo1": "https://imgs.ysscores.com/teams/64/2261693417840.png",
        "name2": "الجيش الملكي",
        "logo2": "https://imgs.ysscores.com/teams/64/4171692205946.png",
        "start_time": 1769270400,
        "end_time": 1769277600,
        "champions": "غير معروف",
        "channel": "غير معروف",
        "commentary": "غير معروف",
        "id": "manual_69742027a43e6",
        "match_status": "لم تبدأ",
        "channel_id": "774e3368-3d2f-40d2-9831-072541a1d619",
        "section": 1
    },
    {
        "name1": "الترجي",
        "logo1": "https://imgs.ysscores.com/teams/64/9451695299186.png",
        "name2": "سيمبا",
        "logo2": "https://imgs.ysscores.com/teams/64/821694715302.png",
        "start_time": 1769270400,
        "end_time": 1769277600,
        "champions": "غير معروف",
        "channel": "غير معروف",
        "commentary": "غير معروف",
        "id": "manual_69742038038ee",
        "match_status": "لم تبدأ",
        "channel_id": "c916c1e3-fb17-4596-94d0-b7da8265bb7f",
        "section": 1
    },
    {
        "name1": "إشبيلية",
        "logo1": "https://imgs.ysscores.com/teams/64/6931690196743.png",
        "name2": "أتلتيك بلباو",
        "logo2": "https://imgs.ysscores.com/teams/64/1061690197944.png",
        "start_time": 1769275800,
        "end_time": 1769283000,
        "champions": "غير معروف",
        "channel": "غير معروف",
        "commentary": "غير معروف",
        "id": "manual_6974205cc4e75",
        "match_status": "لم تبدأ",
        "channel_id": "f0d5144f-9290-40bc-9cee-d7b820431107",
        "section": 1
    },
    {
        "name1": "يونيون برلين",
        "logo1": "https://imgs.ysscores.com/teams/64/6521690288816.png",
        "name2": "دورتموند",
        "logo2": "https://imgs.ysscores.com/teams/64/4201690288818.png",
        "start_time": 1769275800,
        "end_time": 1769283000,
        "champions": "غير معروف",
        "channel": "غير معروف",
        "commentary": "غير معروف",
        "id": "manual_69742074ed106",
        "match_status": "لم تبدأ",
        "channel_id": "9e7d0edd-459c-42a6-ba0b-0c15274fa42c",
        "section": 1
    },
    {
        "name1": "نيوم",
        "logo1": "https://imgs.ysscores.com/teams/64/9361751106662.png",
        "name2": "الأهلي",
        "logo2": "https://imgs.ysscores.com/teams/64/9091751485160.png",
        "start_time": 1769275800,
        "end_time": 1769283000,
        "champions": "غير معروف",
        "channel": "غير معروف",
        "commentary": "غير معروف",
        "id": "manual_69742088b06f5",
        "match_status": "لم تبدأ",
        "channel_id": "7a1287b0-6d27-4040-a79f-98b5b4c6c896",
        "section": 1
    },
    {
        "name1": "بورنموث",
        "logo1": "https://imgs.ysscores.com/teams/64/7651690118769.png",
        "name2": "ليفربول",
        "logo2": "https://imgs.ysscores.com/teams/64/4081724601375.png",
        "start_time": 1769275800,
        "end_time": 1769283000,
        "champions": "غير معروف",
        "channel": "غير معروف",
        "commentary": "غير معروف",
        "id": "manual_697420c493aa9",
        "match_status": "لم تبدأ",
        "channel_id": "d6d19564-6f6b-49a1-b193-dc3c4613b8a3",
        "section": 1
    },
    {
        "name1": "نهضة بركان",
        "logo1": "https://imgs.ysscores.com/teams/64/1121692794477.png",
        "name2": "بيراميدز",
        "logo2": "https://imgs.ysscores.com/teams/64/5771692283569.png",
        "start_time": 1769281200,
        "end_time": 1769288400,
        "champions": "غير معروف",
        "channel": "غير معروف",
        "commentary": "غير معروف",
        "id": "manual_697420e5e394c",
        "match_status": "لم تبدأ",
        "channel_id": "774e3368-3d2f-40d2-9831-072541a1d619",
        "section": 1
    },
    {
        "name1": "اتحاد العاصمة",
        "logo1": "https://imgs.ysscores.com/teams/64/9611695834503.png",
        "name2": "دجوليبا",
        "logo2": "https://imgs.ysscores.com/teams/64/7181732355083.png",
        "start_time": 1769281200,
        "end_time": 1769288400,
        "champions": "غير معروف",
        "channel": "غير معروف",
        "commentary": "غير معروف",
        "id": "manual_697420f62be78",
        "match_status": "لم تبدأ",
        "channel_id": "c0d68f6c-79fd-423e-ac2a-dc9de59a4fd7",
        "section": 1
    },
    {
        "name1": "فياريال",
        "logo1": "https://imgs.ysscores.com/teams/64/7121690196747.png",
        "name2": "ريال مدريد",
        "logo2": "https://imgs.ysscores.com/teams/64/1871690196746.png",
        "start_time": 1769284800,
        "end_time": 1769292000,
        "champions": "غير معروف",
        "channel": "غير معروف",
        "commentary": "غير معروف",
        "id": "manual_6974210c76525",
        "match_status": "لم تبدأ",
        "channel_id": "d6d19564-6f6b-49a1-b193-dc3c4613b8a3",
        "section": 1
    },
    {
        "name1": "وست هام",
        "logo1": "https://imgs.ysscores.com/teams/64/7191690118603.png",
        "name2": "سندرلاند",
        "logo2": "https://imgs.ysscores.com/teams/64/10001690823905.png",
        "start_time": 1769257800,
        "end_time": 1769265000,
        "champions": "غير معروف",
        "channel": "غير معروف",
        "commentary": "غير معروف",
        "id": "manual_69741efe2a47b",
        "match_status": "انتهت",
        "channel_id": "d6d19564-6f6b-49a1-b193-dc3c4613b8a3",
        "section": 1
    }
]