[
    {
        "name1": "لاتسيو",
        "logo1": "https://imgs.ysscores.com/teams/64/5111690283002.png",
        "name2": "نابولي",
        "logo2": "https://imgs.ysscores.com/teams/64/9521720636634.png",
        "start_time": 1767526200,
        "end_time": 1767533400,
        "champions": "غير معروف",
        "channel": "غير معروف",
        "commentary": "غير معروف",
        "id": "manual_695a457d136b8",
        "match_status": "لم تبدأ",
        "channel_id": null,
        "section": null
    },
    {
        "name1": "ليدز يونايتد",
        "logo1": "https://imgs.ysscores.com/teams/64/4691690458244.png",
        "name2": "مان يونايتد",
        "logo2": "https://imgs.ysscores.com/teams/64/4871690119302.png",
        "start_time": 1767529800,
        "end_time": 1767537000,
        "champions": "غير معروف",
        "channel": "غير معروف",
        "commentary": "غير معروف",
        "id": "manual_695a45998b9e0",
        "match_status": "لم تبدأ",
        "channel_id": null,
        "section": null
    },
    {
        "name1": "إشبيلية",
        "logo1": "https://imgs.ysscores.com/teams/64/6931690196743.png",
        "name2": "ليفانتي",
        "logo2": "https://imgs.ysscores.com/teams/64/2601690370530.png",
        "start_time": 1767531600,
        "end_time": 1767538800,
        "champions": "غير معروف",
        "channel": "غير معروف",
        "commentary": "غير معروف",
        "id": "manual_695a45a75fa2d",
        "match_status": "لم تبدأ",
        "channel_id": null,
        "section": null
    },
    {
        "name1": "إيفرتون",
        "logo1": "https://imgs.ysscores.com/teams/64/8461690118694.png",
        "name2": "برينتفورد",
        "logo2": "https://imgs.ysscores.com/teams/64/4791690118957.png",
        "start_time": 1767538800,
        "end_time": 1767546000,
        "champions": "غير معروف",
        "channel": "غير معروف",
        "commentary": "غير معروف",
        "id": "manual_695a45caeaabb",
        "match_status": "لم تبدأ",
        "channel_id": null,
        "section": null
    },
    {
        "name1": "فولهام",
        "logo1": "https://imgs.ysscores.com/teams/64/4711690118927.png",
        "name2": "ليفربول",
        "logo2": "https://imgs.ysscores.com/teams/64/4081724601375.png",
        "start_time": 1767538800,
        "end_time": 1767546000,
        "champions": "غير معروف",
        "channel": "غير معروف",
        "commentary": "غير معروف",
        "id": "manual_695a45d4999a0",
        "match_status": "لم تبدأ",
        "channel_id": null,
        "section": null
    }
]